create_django_react_app/__init__.py
create_django_react_app/create_django_react_app.py
create_django_react_app-0.0.2.dist-info/METADATA
create_django_react_app-0.0.2.dist-info/WHEEL
create_django_react_app-0.0.2.dist-info/entry_points.txt
create_django_react_app-0.0.2.dist-info/top_level.txt
create_django_react_app-0.0.2.dist-info/RECORD
